{
  "date": "20260206",
  "watchlist": [
    {
      "etf_code": "512480.SH",
      "sentiment_score": 0,
      "profit_ratio": 47.883480427488884,
      "nearest_resistance": 1.7080000000000002,
      "micro_caution": true,
      "vpin_rank": 0.23529411764705882,
      "ofi_daily": -0.42954244910265726,
      "vs_max": 0.7866379295604845,
      "extra": {
        "sentiment_score_01": 0.1
      }
    },
    {
      "etf_code": "588200.SH",
      "sentiment_score": 0,
      "profit_ratio": 48.41049880284814,
      "nearest_resistance": 2.592,
      "micro_caution": true,
      "vpin_rank": 0.24074074074074073,
      "ofi_daily": -0.6478884345518788,
      "vs_max": 0.02249816145719282,
      "extra": {
        "sentiment_score_01": 0.1
      }
    },
    {
      "etf_code": "159997.SZ",
      "sentiment_score": 0,
      "profit_ratio": 34.75078441905685,
      "nearest_resistance": 1.732,
      "micro_caution": true,
      "vpin_rank": 0.3620689655172414,
      "ofi_daily": -0.3766154557755363,
      "vs_max": 0.13753353773349508,
      "extra": {
        "sentiment_score_01": 0.1
      }
    },
    {
      "etf_code": "159732.SZ",
      "sentiment_score": 0,
      "profit_ratio": 42.4120648946761,
      "nearest_resistance": 1.174,
      "micro_caution": true,
      "vpin_rank": null,
      "ofi_daily": -0.007422995568156084,
      "vs_max": -0.45574386542893097,
      "extra": {
        "sentiment_score_01": 0.1
      }
    },
    {
      "etf_code": "159852.SZ",
      "sentiment_score": 0,
      "profit_ratio": 15.553065832760055,
      "nearest_resistance": 0.9770000000000001,
      "micro_caution": true,
      "vpin_rank": 0.0625,
      "ofi_daily": -0.7773058641450117,
      "vs_max": 0.0003833285987774442,
      "extra": {
        "sentiment_score_01": 0.1
      }
    },
    {
      "etf_code": "159108.SZ",
      "sentiment_score": 0,
      "profit_ratio": 42.94138043493607,
      "nearest_resistance": 1.145,
      "micro_caution": false,
      "vpin_rank": null,
      "ofi_daily": 1.4879045763044099,
      "vs_max": -1.0070523242038827,
      "extra": {
        "sentiment_score_01": 0.1
      }
    },
    {
      "etf_code": "159998.SZ",
      "sentiment_score": 0,
      "profit_ratio": 27.429004382151177,
      "nearest_resistance": 1.1360000000000001,
      "micro_caution": true,
      "vpin_rank": null,
      "ofi_daily": -0.3762305757527117,
      "vs_max": -0.8629328966160773,
      "extra": {
        "sentiment_score_01": 0.1
      }
    },
    {
      "etf_code": "516510.SH",
      "sentiment_score": 0,
      "profit_ratio": 34.02308692921417,
      "nearest_resistance": 1.907,
      "micro_caution": true,
      "vpin_rank": 0.33962264150943394,
      "ofi_daily": -0.37678923655212593,
      "vs_max": 0.2961222132143576,
      "extra": {
        "sentiment_score_01": 0.1
      }
    },
    {
      "etf_code": "562570.SH",
      "sentiment_score": 0,
      "profit_ratio": 34.260032280353755,
      "nearest_resistance": 1.621,
      "micro_caution": true,
      "vpin_rank": 0.1282051282051282,
      "ofi_daily": -0.5167714857792309,
      "vs_max": 0.4649125655554129,
      "extra": {
        "sentiment_score_01": 0.1
      }
    },
    {
      "etf_code": "562920.SH",
      "sentiment_score": 0,
      "profit_ratio": 39.28127267367097,
      "nearest_resistance": 1.094,
      "micro_caution": true,
      "vpin_rank": 0.6206896551724138,
      "ofi_daily": -0.35401773408516973,
      "vs_max": -0.7694328036060963,
      "extra": {
        "sentiment_score_01": 0.1
      }
    },
    {
      "etf_code": "515880.SH",
      "sentiment_score": 0,
      "profit_ratio": 7.368514030267999,
      "nearest_resistance": 3.141,
      "micro_caution": true,
      "vpin_rank": 0.9636363636363636,
      "ofi_daily": 3.0,
      "vs_max": 2.9374354174664994,
      "extra": {
        "sentiment_score_01": 0.1
      }
    },
    {
      "etf_code": "159811.SZ",
      "sentiment_score": 0,
      "profit_ratio": 31.026516023178203,
      "nearest_resistance": 2.3360000000000003,
      "micro_caution": false,
      "vpin_rank": null,
      "ofi_daily": 0.03144738169901347,
      "vs_max": -1.0314087506343717,
      "extra": {
        "sentiment_score_01": 0.1
      }
    },
    {
      "etf_code": "159363.SZ",
      "sentiment_score": 0,
      "profit_ratio": 57.53235133524254,
      "nearest_resistance": 1.093,
      "micro_caution": true,
      "vpin_rank": 0.07272727272727272,
      "ofi_daily": -2.98665102465433,
      "vs_max": -0.16375985316425545,
      "extra": {
        "sentiment_score_01": 0.1
      }
    },
    {
      "etf_code": "562500.SH",
      "sentiment_score": 0,
      "profit_ratio": 43.21510695240091,
      "nearest_resistance": 1.093,
      "micro_caution": true,
      "vpin_rank": 0.057692307692307696,
      "ofi_daily": -0.4189933719102845,
      "vs_max": -0.5098602334169018,
      "extra": {
        "sentiment_score_01": 0.1
      }
    },
    {
      "etf_code": "159550.SZ",
      "sentiment_score": 0,
      "profit_ratio": 13.481242111380498,
      "nearest_resistance": 1.123,
      "micro_caution": false,
      "vpin_rank": 0.15555555555555556,
      "ofi_daily": 1.7705019820456223,
      "vs_max": -0.05401539548689591,
      "extra": {
        "sentiment_score_01": 0.1
      }
    },
    {
      "etf_code": "512980.SH",
      "sentiment_score": 0,
      "profit_ratio": 17.414804812117435,
      "nearest_resistance": 1.192,
      "micro_caution": false,
      "vpin_rank": 0.6078431372549019,
      "ofi_daily": 0.3632314353034478,
      "vs_max": -0.03757659399652527,
      "extra": {
        "sentiment_score_01": 0.1
      }
    },
    {
      "etf_code": "515030.SH",
      "sentiment_score": 0,
      "profit_ratio": 25.12729054517584,
      "nearest_resistance": 1.941,
      "micro_caution": true,
      "vpin_rank": 0.8666666666666667,
      "ofi_daily": -1.2972786523213748,
      "vs_max": -0.00826942821074185,
      "extra": {
        "sentiment_score_01": 0.1
      }
    },
    {
      "etf_code": "515250.SH",
      "sentiment_score": 0,
      "profit_ratio": 33.572273140531536,
      "nearest_resistance": 1.2360000000000002,
      "micro_caution": true,
      "vpin_rank": null,
      "ofi_daily": -0.7666321507754216,
      "vs_max": -0.9165907071527256,
      "extra": {
        "sentiment_score_01": 0.1
      }
    },
    {
      "etf_code": "159755.SZ",
      "sentiment_score": 0,
      "profit_ratio": 21.92253427661837,
      "nearest_resistance": 1.101,
      "micro_caution": true,
      "vpin_rank": null,
      "ofi_daily": -1.1577297381059746,
      "vs_max": -0.6467672447138698,
      "extra": {
        "sentiment_score_01": 0.1
      }
    },
    {
      "etf_code": "515790.SH",
      "sentiment_score": 0,
      "profit_ratio": 68.72408900948751,
      "nearest_resistance": 1.109,
      "micro_caution": true,
      "vpin_rank": 0.5813953488372093,
      "ofi_daily": -1.1146692608360194,
      "vs_max": 1.7159378745861071,
      "extra": {
        "sentiment_score_01": 0.1
      }
    },
    {
      "etf_code": "159566.SZ",
      "sentiment_score": 0,
      "profit_ratio": 19.257949761478777,
      "nearest_resistance": 2.138,
      "micro_caution": true,
      "vpin_rank": 0.8421052631578947,
      "ofi_daily": -1.3067369575144918,
      "vs_max": -1.9922519215656772e-16,
      "extra": {
        "sentiment_score_01": 0.1
      }
    },
    {
      "etf_code": "588830.SH",
      "sentiment_score": 0,
      "profit_ratio": 64.17304955423701,
      "nearest_resistance": null,
      "micro_caution": true,
      "vpin_rank": 0.8913043478260869,
      "ofi_daily": -0.5495025248567633,
      "vs_max": 0.7665439823990392,
      "extra": {
        "sentiment_score_01": 0.1
      }
    },
    {
      "etf_code": "588010.SH",
      "sentiment_score": 0,
      "profit_ratio": 43.33781682148712,
      "nearest_resistance": 0.988,
      "micro_caution": false,
      "vpin_rank": 0.5227272727272727,
      "ofi_daily": 1.4054715277145489,
      "vs_max": -0.3707147174027685,
      "extra": {
        "sentiment_score_01": 0.1
      }
    },
    {
      "etf_code": "159638.SZ",
      "sentiment_score": 0,
      "profit_ratio": 39.658014150612104,
      "nearest_resistance": 1.155,
      "micro_caution": true,
      "vpin_rank": null,
      "ofi_daily": -0.8460116573876441,
      "vs_max": -1.2478638032359561,
      "extra": {
        "sentiment_score_01": 0.1
      }
    },
    {
      "etf_code": "159667.SZ",
      "sentiment_score": 0,
      "profit_ratio": 50.75234018897557,
      "nearest_resistance": 1.722,
      "micro_caution": true,
      "vpin_rank": null,
      "ofi_daily": -0.6739122950906603,
      "vs_max": -1.7855267773357144,
      "extra": {
        "sentiment_score_01": 0.1
      }
    },
    {
      "etf_code": "560280.SH",
      "sentiment_score": 0,
      "profit_ratio": 92.3450853982638,
      "nearest_resistance": null,
      "micro_caution": true,
      "vpin_rank": 0.17543859649122806,
      "ofi_daily": -2.075924432275325,
      "vs_max": 0.3292319431155693,
      "extra": {
        "sentiment_score_01": 0.1
      }
    },
    {
      "etf_code": "512710.SH",
      "sentiment_score": 0,
      "profit_ratio": 55.243122296898726,
      "nearest_resistance": 0.865,
      "micro_caution": true,
      "vpin_rank": null,
      "ofi_daily": -0.9718304339966214,
      "vs_max": -1.1806923961074443,
      "extra": {
        "sentiment_score_01": 0.1
      }
    },
    {
      "etf_code": "159227.SZ",
      "sentiment_score": 0,
      "profit_ratio": 51.08933217614491,
      "nearest_resistance": 1.4789999999999999,
      "micro_caution": true,
      "vpin_rank": 0.47368421052631576,
      "ofi_daily": -0.005921202805551261,
      "vs_max": -1.8061213520471275,
      "extra": {
        "sentiment_score_01": 0.1
      }
    },
    {
      "etf_code": "159206.SZ",
      "sentiment_score": 0,
      "profit_ratio": 22.922438071009246,
      "nearest_resistance": 1.925,
      "micro_caution": true,
      "vpin_rank": 0.4067796610169492,
      "ofi_daily": -0.4265882959679,
      "vs_max": -1.4521991572468391,
      "extra": {
        "sentiment_score_01": 0.1
      }
    },
    {
      "etf_code": "512010.SH",
      "sentiment_score": 100,
      "profit_ratio": 32.061093708043956,
      "nearest_resistance": 0.385,
      "micro_caution": false,
      "vpin_rank": 0.32142857142857145,
      "ofi_daily": 1.2715939120204327,
      "vs_max": 1.568403127931081,
      "extra": {
        "sentiment_score_01": 0.9
      }
    },
    {
      "etf_code": "159992.SZ",
      "sentiment_score": 0,
      "profit_ratio": 13.113474871030778,
      "nearest_resistance": 0.8600000000000001,
      "micro_caution": false,
      "vpin_rank": 0.24,
      "ofi_daily": 0.08124175140403743,
      "vs_max": 0.3259985141753415,
      "extra": {
        "sentiment_score_01": 0.1
      }
    },
    {
      "etf_code": "159883.SZ",
      "sentiment_score": 0,
      "profit_ratio": 24.69924807720426,
      "nearest_resistance": 0.525,
      "micro_caution": false,
      "vpin_rank": 0.5106382978723404,
      "ofi_daily": 0.13885989788160452,
      "vs_max": 0.32032642475187106,
      "extra": {
        "sentiment_score_01": 0.1
      }
    },
    {
      "etf_code": "560080.SH",
      "sentiment_score": 100,
      "profit_ratio": 48.96278179571014,
      "nearest_resistance": null,
      "micro_caution": true,
      "vpin_rank": 0.9024390243902439,
      "ofi_daily": 2.7415307612105564,
      "vs_max": 1.6637090720779943,
      "extra": {
        "sentiment_score_01": 0.9
      }
    },
    {
      "etf_code": "159859.SZ",
      "sentiment_score": 0,
      "profit_ratio": 26.656329750682485,
      "nearest_resistance": 0.399,
      "micro_caution": false,
      "vpin_rank": 0.3269230769230769,
      "ofi_daily": 0.6479356270354427,
      "vs_max": 0.05990263518570471,
      "extra": {
        "sentiment_score_01": 0.1
      }
    },
    {
      "etf_code": "159928.SZ",
      "sentiment_score": 100,
      "profit_ratio": 69.73751072895314,
      "nearest_resistance": 0.831,
      "micro_caution": false,
      "vpin_rank": 0.5094339622641509,
      "ofi_daily": 0.15801419854452695,
      "vs_max": 2.047007589812405,
      "extra": {
        "sentiment_score_01": 0.9
      }
    },
    {
      "etf_code": "515170.SH",
      "sentiment_score": 0,
      "profit_ratio": 71.69812588886529,
      "nearest_resistance": null,
      "micro_caution": false,
      "vpin_rank": 0.1590909090909091,
      "ofi_daily": 1.9014012037505514,
      "vs_max": 2.6683539383033272,
      "extra": {
        "sentiment_score_01": 0.1
      }
    },
    {
      "etf_code": "512690.SH",
      "sentiment_score": 0,
      "profit_ratio": 71.64919527396259,
      "nearest_resistance": 0.585,
      "micro_caution": false,
      "vpin_rank": 0.18518518518518517,
      "ofi_daily": 0.9783021509635823,
      "vs_max": 2.169441135292525,
      "extra": {
        "sentiment_score_01": 0.1
      }
    },
    {
      "etf_code": "159996.SZ",
      "sentiment_score": 0,
      "profit_ratio": 63.04311813783535,
      "nearest_resistance": 1.58,
      "micro_caution": true,
      "vpin_rank": 0.7169811320754716,
      "ofi_daily": -0.6276289152523452,
      "vs_max": -0.5896940079569897,
      "extra": {
        "sentiment_score_01": 0.1
      }
    },
    {
      "etf_code": "159825.SZ",
      "sentiment_score": 0,
      "profit_ratio": 42.55409343849116,
      "nearest_resistance": 0.8450000000000001,
      "micro_caution": true,
      "vpin_rank": 0.6666666666666666,
      "ofi_daily": -0.7085932272683161,
      "vs_max": 0.4948835455273921,
      "extra": {
        "sentiment_score_01": 0.1
      }
    },
    {
      "etf_code": "159865.SZ",
      "sentiment_score": 0,
      "profit_ratio": 25.369550076504726,
      "nearest_resistance": 0.633,
      "micro_caution": false,
      "vpin_rank": 0.5128205128205128,
      "ofi_daily": 0.16754313942217358,
      "vs_max": 0.3196757735361418,
      "extra": {
        "sentiment_score_01": 0.1
      }
    },
    {
      "etf_code": "512880.SH",
      "sentiment_score": 0,
      "profit_ratio": 18.121957632066316,
      "nearest_resistance": 1.202,
      "micro_caution": false,
      "vpin_rank": 0.043478260869565216,
      "ofi_daily": 0.2336204477410235,
      "vs_max": -1.470478426214886e-16,
      "extra": {
        "sentiment_score_01": 0.1
      }
    },
    {
      "etf_code": "512800.SH",
      "sentiment_score": 100,
      "profit_ratio": 37.13447949180473,
      "nearest_resistance": 0.819,
      "micro_caution": true,
      "vpin_rank": 0.775,
      "ofi_daily": 2.2797095367788245,
      "vs_max": 1.497827730056918,
      "extra": {
        "sentiment_score_01": 0.9
      }
    },
    {
      "etf_code": "512070.SH",
      "sentiment_score": 0,
      "profit_ratio": 50.897943678056166,
      "nearest_resistance": 0.986,
      "micro_caution": true,
      "vpin_rank": 0.8269230769230769,
      "ofi_daily": 0.1898391236664302,
      "vs_max": -0.6096698870911321,
      "extra": {
        "sentiment_score_01": 0.1
      }
    },
    {
      "etf_code": "512200.SH",
      "sentiment_score": 0,
      "profit_ratio": 64.59983140481961,
      "nearest_resistance": null,
      "micro_caution": true,
      "vpin_rank": 0.6956521739130435,
      "ofi_daily": -0.15808493819507521,
      "vs_max": 0.8800457667926188,
      "extra": {
        "sentiment_score_01": 0.1
      }
    },
    {
      "etf_code": "516970.SH",
      "sentiment_score": 0,
      "profit_ratio": 56.69312293564369,
      "nearest_resistance": 1.236,
      "micro_caution": true,
      "vpin_rank": 0.5,
      "ofi_daily": -1.2817172346896617,
      "vs_max": -0.8249459830509187,
      "extra": {
        "sentiment_score_01": 0.1
      }
    },
    {
      "etf_code": "512400.SH",
      "sentiment_score": 0,
      "profit_ratio": 37.66096194101115,
      "nearest_resistance": 2.18,
      "micro_caution": true,
      "vpin_rank": 0.5862068965517241,
      "ofi_daily": -1.2100441178398662,
      "vs_max": 0.3204466390949877,
      "extra": {
        "sentiment_score_01": 0.1
      }
    },
    {
      "etf_code": "516150.SH",
      "sentiment_score": 0,
      "profit_ratio": 40.53251118318497,
      "nearest_resistance": 2.003,
      "micro_caution": true,
      "vpin_rank": 0.55,
      "ofi_daily": -0.9926112960152763,
      "vs_max": 0.08683427102416454,
      "extra": {
        "sentiment_score_01": 0.1
      }
    },
    {
      "etf_code": "515220.SH",
      "sentiment_score": 0,
      "profit_ratio": 66.9195095108048,
      "nearest_resistance": 1.204,
      "micro_caution": false,
      "vpin_rank": 0.2894736842105263,
      "ofi_daily": 0.5319172781524513,
      "vs_max": 1.639360174477811,
      "extra": {
        "sentiment_score_01": 0.1
      }
    },
    {
      "etf_code": "515210.SH",
      "sentiment_score": 0,
      "profit_ratio": 56.50405326996933,
      "nearest_resistance": 1.508,
      "micro_caution": true,
      "vpin_rank": 0.13157894736842105,
      "ofi_daily": -3.0,
      "vs_max": 0.2596464083800416,
      "extra": {
        "sentiment_score_01": 0.1
      }
    },
    {
      "etf_code": "159870.SZ",
      "sentiment_score": 0,
      "profit_ratio": 46.30395198755675,
      "nearest_resistance": 0.874,
      "micro_caution": true,
      "vpin_rank": 0.27450980392156865,
      "ofi_daily": -1.115216602397854,
      "vs_max": 0.35899975081799335,
      "extra": {
        "sentiment_score_01": 0.1
      }
    }
  ]
}